mailscrambler/__init__.py
mailscrambler/mailscrambler.py
mailscrambler-0.1.2.dist-info/LICENSE
mailscrambler-0.1.2.dist-info/METADATA
mailscrambler-0.1.2.dist-info/WHEEL
mailscrambler-0.1.2.dist-info/top_level.txt
mailscrambler-0.1.2.dist-info/RECORD
