Metadata-Version: 2.1
Name: mailscrambler
Version: 0.1.2
Summary: E-mail scrambling library
Home-page: https://www.github.com/deme3/emailscrambler
Author: Demetrio Battaglia
Author-email: Demetrio Battaglia <deme3.iot@gmail.com>
Project-URL: Homepage, https://github.com/deme3/emailscrambler
Project-URL: Bug Tracker, https://github.com/deme3/emailscrambler/issues
Classifier: Programming Language :: Python :: 3
Classifier: License :: OSI Approved :: MIT License
Classifier: Operating System :: OS Independent
Requires-Python: >=3.7
License-File: LICENSE
